pygmdl/__init__.py
pygmdl/config.py
pygmdl/converter.py
pygmdl/downloader.py
pygmdl/gmapper.py
pygmdl-0.2.3.dist-info/licenses/LICENSE.md
pygmdl-0.2.3.dist-info/METADATA
pygmdl-0.2.3.dist-info/WHEEL
pygmdl-0.2.3.dist-info/top_level.txt
pygmdl-0.2.3.dist-info/RECORD
