Metadata-Version: 2.4
Name: pygmdl
Version: 0.2.3
Summary: Download satellite images from Google Maps.
Author-email: iwatkot <iwatkot@gmail.com>
License: MIT License
Project-URL: Homepage, https://github.com/iwatkot/pygmdl
Project-URL: Repository, https://github.com/iwatkot/pygmdl
Keywords: googlemaps,satellite,images,download
Classifier: Programming Language :: Python :: 3.11
Classifier: Programming Language :: Python :: 3.12
Classifier: License :: OSI Approved :: MIT License
Classifier: Operating System :: OS Independent
License-File: LICENSE.md
Requires-Dist: Pillow
Requires-Dist: pyproj
Requires-Dist: geopy
Requires-Dist: tqdm
Requires-Dist: requests
Dynamic: license-file
